aibenchmark/__init__.py
aibenchmark/benchmark.py
aibenchmark/dataset.py
aibenchmark/decompress.py
aibenchmark/exceptions.py
aibenchmark/metrics.py
aibenchmark/scrapers/__init__.py
aibenchmark/scrapers/papers_with_code_scraper.py
aibench-0.0.5.dist-info/METADATA
aibench-0.0.5.dist-info/WHEEL
aibench-0.0.5.dist-info/top_level.txt
aibench-0.0.5.dist-info/RECORD
